tdx2csv/__init__.py
tdx2csv/__main__.py
tdx2csv/tdx2csv.py
tdx2csv-0.1.1.dist-info/LICENSE
tdx2csv-0.1.1.dist-info/METADATA
tdx2csv-0.1.1.dist-info/WHEEL
tdx2csv-0.1.1.dist-info/entry_points.txt
tdx2csv-0.1.1.dist-info/top_level.txt
tdx2csv-0.1.1.dist-info/RECORD
